{
  "profile": "Patient Profile: Alex Reed\n\nBackstory:\nAlex Reed, a 62-year-old Caucasian individual, was born and raised in a small Midwestern town. Alex's childhood was marked by financial instability and a tumultuous family life, with a history of mental illness running through the generations. Despite these challenges, Alex found solace in writing and caring for the family's pets, which cultivated a deep sense of empathy and resilience.\n\nAfter graduating from high school, Alex moved to a nearby city and began working in a clerical position at a local manufacturing company. Over the years, Alex worked their way up to a managerial role, finding satisfaction in helping colleagues and maintaining a sense of order in the workplace. However, the long hours and high-pressure environment began to take a toll on Alex's mental well-being.\n\nThroughout adulthood, Alex struggled with substance abuse, using alcohol to cope with the stress of work and the emotional burden of caring for an aging parent with dementia. After a particularly difficult period, Alex sought help and has been in recovery for the past five years. Despite this progress, the cumulative impact of these life events, combined with a genetic predisposition to mental illness, has led to the development of moderate depression.\n\nCurrent Life Situation:\nAlex currently lives alone in a small apartment with their two cats, who provide a sense of companionship and comfort. Work continues to be a significant source of stress, with long hours and a demanding workload. Alex often feels isolated and disconnected from colleagues, struggling to maintain the extroverted persona that once came so easily.\n\nIn their personal life, Alex has a few close friends but struggles to maintain regular contact, often canceling plans due to fatigue or a lack of interest. Alex finds solace in online support communities, where they can connect with others who understand the challenges of depression and recovery. Writing and photography remain important creative outlets, but Alex often lacks the motivation to engage in these activities.\n\nDepressive Symptoms:\nAlex's depression is characterized by persistent feelings of sadness, hopelessness, and a lack of energy. They have difficulty sleeping, often waking up feeling unrefreshed and struggling to get out of bed in the morning. Alex's appetite has decreased, and they have lost interest in the hobbies and activities that once brought joy.\n\nAt work, Alex struggles to concentrate and make decisions, leading to a sense of inadequacy and self-doubt. They often withdraw from social interactions, feeling overwhelmed and disconnected from others. Alex's low engagement level is evident in their reluctance to seek help or discuss their struggles with friends or family.\n\nOnset and Progression:\nAlex's depression began to emerge in their late 50s, following a series of stressful life events. The combination of workplace burnout, caring for an ill parent, and the challenges of substance abuse recovery culminated in a gradual decline in mental health. At first, Alex dismissed their symptoms as temporary stress, but as the feelings of hopelessness and fatigue persisted, they began to recognize the presence of depression.\n\nPrevious Treatment History:\nAlex has not previously sought professional help for their depression, largely due to a sense of stigma and a belief that they should be able to manage their emotions independently. However, Alex's involvement in online support communities has exposed them to the idea of therapy, and they are beginning to consider reaching out for professional support.\n\nCoping Mechanisms:\nAlex's primary coping mechanisms involve helping others and social withdrawal. At work, Alex finds temporary relief in assisting colleagues and maintaining a sense of order, but this often comes at the expense of their own well-being. In their personal life, Alex tends to withdraw from social interactions, seeking solace in the company of their pets and the anonymity of online support groups.\n\nSocial Support:\nAlex's social support system is primarily composed of online communities focused on depression and recovery. These platforms provide a sense of connection and understanding, allowing Alex to share their experiences and learn from others who have faced similar challenges. However, Alex struggles to maintain close relationships in their personal life, often feeling disconnected from friends and family.\n\nPersonal Strengths and Resources:\nDespite the challenges of depression, Alex possesses a number of personal strengths and resources. Their resilience, developed through a lifetime of adversity, has enabled them to overcome significant obstacles, including substance abuse. Alex's empathy and desire to help others are valuable assets, providing a sense of purpose and connection.\n\nPotential Challenges in Therapy:\nOne potential challenge in therapy may be Alex's reluctance to open up and share their emotions. Their easy-going persona and tendency to focus on helping others may make it difficult for them to prioritize their own needs and engage in the vulnerable work of therapy. Additionally, Alex's low engagement level and social withdrawal may hinder their ability to fully participate in the therapeutic process.\n\nTreatment Goals:\nAlex's treatment goals should focus on developing healthy coping mechanisms, improving self-care, and fostering a sense of connection and purpose. Specific goals may include:\n\n1. Developing a daily routine that prioritizes self-care, including regular sleep patterns, healthy eating, and exercise.\n2. Exploring new hobbies and creative outlets that provide a sense of joy and accomplishment.\n3. Building and maintaining supportive relationships, both online and in-person.\n4. Learning to set healthy boundaries at work and prioritize personal well-being.\n5. Developing emotional regulation skills and healthy coping mechanisms for managing stress and difficult emotions.\n6. Challenging negative thought patterns and beliefs that contribute to feelings of hopelessness and inadequacy.\n7. Cultivating a sense of self-compassion and acceptance, recognizing the strength and resilience inherent in their journey.\n\nCultural, Religious, or Personal Beliefs:\nAlex does not identify with any particular religious or cultural beliefs that significantly influence their experience of depression or approach to treatment. However, their personal beliefs around self-reliance and the stigma of mental illness may impact their willingness to seek help and engage in therapy. Addressing these beliefs and providing psychoeducation around the nature of depression will be an important aspect of treatment.",
  "characteristics": {
    "Age": "56-65",
    "Gender": "Other",
    "Ethnicity": "Caucasian",
    "Education": "High School",
    "Occupation": "White-collar worker",
    "Symptom_Severity": "Moderate",
    "Engagement_Level": "Low",
    "Life_Events": [
      "Substance abuse recovery",
      "Workplace stress or burnout",
      "Caring for an ill family member"
    ],
    "Family_Background": "Family history of mental illness",
    "Hobbies_Interests": [
      "Animal care or pet ownership",
      "Writing",
      "Board games",
      "Photography"
    ],
    "Social_Support": "Online support communities",
    "Personality_Traits": [
      "Resilient",
      "Extroverted",
      "Easy-going"
    ],
    "Coping_Mechanisms": [
      "Helping others",
      "Social withdrawal"
    ]
  }
}