{
  "profile": "Patient Profile: Jamie Lin\n\nBackstory:\nJamie Lin is a 62-year-old non-binary individual of East Asian descent. Born and raised in a conservative religious family, Jamie faced challenges in reconciling their gender identity with the expectations of their upbringing. Despite these difficulties, Jamie pursued higher education, earning a doctoral degree in musicology and enjoying a fulfilling career as a university professor.\n\nJamie's life took a turn when they became a parent through adoption in their late 40s. The responsibilities of parenthood, coupled with the challenges of being a non-binary person in a conservative community, led to increased stress and financial difficulties. These factors contributed to the onset of mild depressive symptoms.\n\nCurrent Life Situation:\nSince retiring from their teaching position three years ago, Jamie has struggled to find a sense of purpose and meaning in their daily life. Living alone in a small apartment, Jamie often feels isolated and disconnected from their cultural and ethnic community. They have difficulty maintaining relationships and engaging in social activities due to their depressive symptoms.\n\nJamie's daily life is centered around caring for their teenage child, who is preparing to leave for college. While Jamie finds joy in playing musical instruments and reading, they often lack the motivation and energy to engage in these hobbies consistently.\n\nDepressive Symptoms and Impact:\nJamie experiences mild depressive symptoms, including persistent low mood, fatigue, difficulty concentrating, and feelings of worthlessness. These symptoms have led to a decrease in their overall functioning and quality of life.\n\nThe lack of structure and social interaction in Jamie's daily life exacerbates their feelings of loneliness and isolation. They often struggle with decision-making and find it challenging to maintain a consistent routine, which further contributes to their depressive symptoms.\n\nOnset and Progression of Depression:\nJamie's depressive symptoms first emerged in their early 50s, following the adoption of their child and the subsequent financial difficulties. The stress of parenthood, combined with the lack of acceptance from their conservative family and community, led to a gradual onset of mild depression.\n\nOver the years, Jamie's symptoms have fluctuated, with periods of improvement followed by setbacks triggered by life stressors, such as their child's transition to adolescence and their own retirement.\n\nPrevious Treatment History:\nJamie has never sought professional help for their depression, largely due to the stigma associated with mental health in their cultural background. They have relied on their own coping mechanisms and the support of a few close friends within their cultural community.\n\nCoping Mechanisms and Effectiveness:\nJamie's primary coping mechanisms include problem-solving and emotional eating. While their problem-solving skills have helped them navigate some of the challenges of parenthood and retirement, emotional eating has led to weight gain and feelings of guilt, exacerbating their depressive symptoms.\n\nJamie's adventurous and empathetic personality traits have also played a role in their coping. They find solace in exploring new hobbies and connecting with others who share similar experiences, but their depressive symptoms often hinder their ability to fully engage in these activities.\n\nSocial Support System:\nJamie's social support system primarily consists of a small group of friends from their cultural and ethnic community. While these friends provide a sense of belonging and understanding, Jamie often feels disconnected from them due to their non-binary identity and the stigma surrounding mental health in their community.\n\nJamie has not disclosed their depressive symptoms to their family, fearing judgment and rejection. This lack of familial support contributes to their sense of isolation and exacerbates their symptoms.\n\nPersonal Strengths and Resilience Factors:\nDespite their challenges, Jamie possesses several strengths and resilience factors that can be leveraged in therapy. Their high level of education, problem-solving skills, and empathetic nature provide a foundation for personal growth and self-reflection.\n\nJamie's passion for music and reading also serves as potential sources of comfort and self-expression, which can be incorporated into their treatment plan.\n\nPotential Challenges in Therapy:\nJamie's cultural background and the stigma associated with mental health may present challenges in therapy. They may initially be reluctant to disclose personal information or discuss their feelings openly, fearing judgment or rejection from the therapist.\n\nAdditionally, Jamie's non-binary identity and the lack of acceptance from their family and community may contribute to feelings of shame and isolation, making it difficult for them to trust and engage in the therapeutic process.\n\nTreatment Goals:\n1. Develop healthy coping mechanisms to replace emotional eating and improve overall well-being.\n2. Increase social engagement and connection with supportive individuals, both within and outside of their cultural community.\n3. Explore and process the impact of their family background and cultural identity on their mental health and sense of self.\n4. Improve communication skills and assertiveness to foster healthier relationships and boundaries.\n5. Rediscover a sense of purpose and meaning in life following retirement and the impending empty nest phase.\n6. Develop a more compassionate and accepting relationship with themselves, acknowledging their strengths and resilience.\n\nCultural, Religious, or Personal Beliefs:\nJamie's cultural and religious upbringing may influence their experience of depression and approach to treatment. They may hold beliefs about the importance of self-sufficiency and the shame associated with mental health struggles, which could impact their willingness to seek help and engage in therapy.\n\nAdditionally, Jamie's non-binary identity may be at odds with the traditional gender roles and expectations of their cultural background, contributing to feelings of alienation and internal conflict.\n\nIn therapy, it will be crucial to acknowledge and explore these cultural and personal factors, working collaboratively with Jamie to develop a treatment plan that respects their values and beliefs while fostering personal growth and healing.",
  "characteristics": {
    "Age": "56-65",
    "Gender": "Non-binary",
    "Ethnicity": "East Asian",
    "Education": "Doctoral Degree",
    "Occupation": "Retired",
    "Symptom_Severity": "Mild",
    "Engagement_Level": "Medium",
    "Life_Events": [
      "Financial difficulties",
      "Becoming a parent"
    ],
    "Family_Background": "Religious or conservative upbringing",
    "Hobbies_Interests": [
      "Playing musical instruments",
      "Reading"
    ],
    "Social_Support": "Cultural or ethnic community",
    "Personality_Traits": [
      "Adventurous",
      "Empathetic"
    ],
    "Coping_Mechanisms": [
      "Problem-solving",
      "Emotional eating"
    ]
  }
}