{
  "profile": "Patient Profile: Alex Ramirez\n\nBackstory:\nAlex Ramirez, a 52-year-old non-binary individual of Hispanic descent, was born and raised in a tight-knit community in the suburbs of Chicago. Alex's family life was marked by the struggles of addiction, with both parents battling substance abuse throughout their childhood. Despite these challenges, Alex found solace in academics, displaying a keen intellect and a passion for learning from a young age.\n\nDetermined to break free from the cycle of addiction that plagued their family, Alex pursued higher education, ultimately earning a Doctoral Degree in Psychology. During their academic journey, Alex faced significant financial difficulties, often working multiple jobs to make ends meet while also dealing with the pressures of a rigorous academic program.\n\nAfter completing their education, Alex secured a position as a clinical psychologist at a reputable mental health clinic in Chicago. However, the demands of the job, coupled with the lingering trauma of their childhood, began to take a toll on Alex's mental well-being. Seeking a fresh start, Alex made the difficult decision to relocate to a new city, accepting a position at a university in San Francisco.\n\nCurrent Life Situation:\nAlex has been living in San Francisco for the past year, working as a psychology professor at a prestigious university. Despite their professional success, Alex has struggled to adapt to the new environment, feeling isolated and disconnected from the support networks they had built in Chicago. The combination of the high cost of living in San Francisco and the financial burden of the recent move has left Alex grappling with significant financial stress.\n\nIn their personal life, Alex has found it challenging to form new friendships and romantic relationships, often feeling anxious and reserved in social situations. They have turned to video games and the companionship of their rescue dog, Luna, as their primary sources of comfort and stress relief.\n\nDepressive Symptoms and Impact:\nAlex's depressive symptoms have been mild but persistent, characterized by a pervasive sense of sadness, low energy, and a lack of interest in activities they once enjoyed. They often experience feelings of worthlessness and guilt, questioning their decision to leave their support network behind in Chicago.\n\nThe symptoms have begun to impact Alex's professional life, with the once confident and optimistic professor now struggling to engage with students and colleagues. Alex's reserved nature has made it difficult for them to reach out for help, and they often find themselves avoiding social interactions and professional opportunities.\n\nOnset and Progression of Depression:\nThe onset of Alex's depression can be traced back to their childhood, with the early experiences of familial addiction and financial instability laying the foundation for their current struggles. The pressure to succeed academically and financially, coupled with the lack of a stable support system, likely contributed to the development of their depressive symptoms.\n\nThe recent move to San Francisco and the associated financial difficulties have exacerbated Alex's depression, with the lack of social support and feelings of isolation intensifying their symptoms.\n\nPrevious Treatment History:\nAlex has not previously sought treatment for their depression, largely due to their reserved nature and the stigma surrounding mental health in their family and cultural background. They have a general understanding of therapy and its potential benefits, given their professional background, but have been hesitant to engage in treatment themselves.\n\nCoping Mechanisms and Effectiveness:\nAlex has relied on a combination of coping mechanisms to manage their depressive symptoms, with varying degrees of effectiveness. They often turn to video games as a means of escape and distraction, finding temporary relief in the immersive worlds and the sense of accomplishment that comes with completing in-game challenges.\n\nHowever, Alex's tendency to cope through emotional eating and avoidance has had a negative impact on their overall well-being. They often find themselves consuming unhealthy foods in an attempt to self-soothe, leading to feelings of guilt and worsening their self-esteem. Additionally, their avoidance of social situations and professional opportunities has hindered their ability to form meaningful connections and advance their career.\n\nSocial Support System:\nDespite the challenges of the recent move, Alex has begun to explore the LGBTQ+ community in San Francisco, attending a few support group meetings for non-binary individuals. They have found a sense of understanding and acceptance within this community, though they have yet to form close friendships or relationships.\n\nAlex's primary source of support comes from their younger sibling, Mia, who still lives in Chicago. Mia, a successful therapist, has been a constant source of encouragement and understanding for Alex, urging them to seek professional help for their depression.\n\nPersonal Strengths and Resilience Factors:\nAlex possesses a number of personal strengths and resilience factors that can be leveraged in their recovery journey. Their intelligence, academic achievements, and professional success demonstrate a strong sense of determination and resilience in the face of adversity.\n\nAdditionally, Alex's love for animals, particularly their bond with their rescue dog, Luna, provides a source of unconditional love and comfort. This connection to animals could be a valuable resource in their recovery, offering a sense of purpose and emotional support.\n\nChallenges in Therapy:\nGiven Alex's background and personality, there are several potential challenges that may arise in therapy. Their reserved nature and difficulty opening up to others may hinder their ability to form a strong therapeutic alliance and engage fully in the treatment process.\n\nAdditionally, the stigma surrounding mental health in Alex's family and cultural background may contribute to feelings of shame or reluctance to seek help. Their financial difficulties and the associated stress may also impact their ability to prioritize and engage in therapy consistently.\n\nTreatment Goals:\nAlex's treatment goals should be personalized to align with their unique life circumstances, values, and personal strengths. Potential goals may include:\n\n1. Developing healthier coping mechanisms to replace emotional eating and avoidance, such as engaging in regular exercise, practicing mindfulness, or pursuing creative hobbies.\n2. Gradually increasing social engagement and forming meaningful connections within the LGBTQ+ community and their professional network.\n3. Addressing the underlying trauma and family dynamics related to addiction, working towards a greater sense of self-compassion and understanding.\n4. Improving financial management skills and developing a plan to reduce financial stress and increase stability.\n5. Exploring and challenging the cultural and personal beliefs that contribute to the stigma surrounding mental health and seeking help.\n\nCultural and Personal Beliefs:\nAlex's Hispanic heritage and the cultural values surrounding mental health may influence their experience of depression and their approach to treatment. The stigma associated with mental illness in many Hispanic communities, coupled with the emphasis on self-reliance and the expectation to cope with challenges independently, may contribute to Alex's reluctance to seek help.\n\nAdditionally, Alex's non-binary identity and the potential lack of understanding or acceptance within their family and cultural community may exacerbate feelings of isolation and contribute to their depressive symptoms. Addressing these cultural and personal factors in therapy will be crucial in developing a comprehensive and culturally sensitive treatment plan.\n\nConclusion:\nAlex Ramirez is a complex individual whose experiences, background, and personal characteristics have shaped their current struggle with depression. By considering the unique interplay of their life events, family dynamics, coping mechanisms, and cultural factors, a personalized and comprehensive treatment approach can be developed to support Alex in their journey towards improved mental health and well-being.",
  "characteristics": {
    "Age": "46-55",
    "Gender": "Non-binary",
    "Ethnicity": "Hispanic",
    "Education": "Doctoral Degree",
    "Occupation": "White-collar worker",
    "Symptom_Severity": "Mild",
    "Engagement_Level": "Low",
    "Life_Events": [
      "Financial difficulties",
      "Academic struggles",
      "Moving to a new city"
    ],
    "Family_Background": "Family affected by addiction",
    "Hobbies_Interests": [
      "Video games",
      "Animal care or pet ownership"
    ],
    "Social_Support": "LGBTQ+ support network",
    "Personality_Traits": [
      "Confident",
      "Anxious",
      "Optimistic",
      "Reserved"
    ],
    "Coping_Mechanisms": [
      "Anger or aggression",
      "Emotional eating",
      "Avoidance"
    ]
  }
}