{
  "profile": "Patient Profile: Jamie Doe\n\nBackstory:\nJamie Doe is a 68-year-old non-binary individual of Caucasian descent. Growing up as an only child in a small, conservative town, Jamie often felt isolated and struggled with their identity from a young age. Despite these challenges, Jamie was resilient and found solace in their love for the outdoors, particularly hiking and camping.\n\nJamie attended college but dropped out after two years due to financial difficulties and a lack of direction. They worked various jobs over the years, but none that provided a sense of fulfillment or purpose. At the age of 35, Jamie married their long-time partner, and they attempted to start a family. However, after several years of infertility struggles and a devastating miscarriage, Jamie and their partner separated.\n\nCurrent Life Situation:\nCurrently, Jamie is unemployed after being laid off from their job at a local retail store due to the economic downturn. They live alone in a small apartment in a tight-knit neighborhood. Jamie's days are often unstructured, filled with excessive sleeping and emotional eating. Despite their love for hiking and camping, Jamie rarely engages in these activities anymore due to a lack of motivation and energy.\n\nDepressive Symptoms and Impact:\nJamie's depressive symptoms are severe and have significantly impacted their daily life. They experience persistent feelings of sadness, hopelessness, and worthlessness. Jamie often struggles with insomnia, finding it difficult to fall and stay asleep. They have lost interest in their once-beloved hobbies, such as dancing, singing, and cooking. Jamie's appetite has decreased, and they often forget to eat or turn to emotional eating for comfort.\n\nOnset and Progression of Depression:\nJamie's depression first emerged in their early 30s, following their infertility struggles and miscarriage. However, it was not until their recent job loss that their symptoms escalated to a severe level. The lack of structure and purpose in Jamie's life has exacerbated their feelings of worthlessness and hopelessness.\n\nPrevious Treatment History:\nJamie has never sought professional help for their depression. They have a skeptical attitude towards therapy, believing that they should be able to overcome their struggles on their own. However, Jamie's neighbor, who has become a close friend, has encouraged them to consider seeking help.\n\nCoping Mechanisms and Effectiveness:\nJamie's primary coping mechanisms include journaling, emotional eating, and excessive sleeping. While journaling provides a temporary outlet for their emotions, the emotional eating and excessive sleeping often leave Jamie feeling worse in the long run. Their extroverted nature and resilience have helped them maintain some level of engagement with their hobbies and neighborhood connections, but these coping mechanisms are not sufficient to alleviate their severe depressive symptoms.\n\nSocial Support System:\nJamie's main source of social support comes from their neighborhood connections. They have developed close friendships with several neighbors who regularly check in on them and invite them to community events. However, Jamie often declines these invitations due to their lack of energy and motivation.\n\nPersonal Strengths and Resilience Factors:\nDespite their struggles, Jamie possesses several strengths and resilience factors. Their love for the outdoors and physical activities like yoga and meditation have the potential to be powerful tools in their recovery. Jamie's extroverted nature and ability to form connections with others can also be leveraged in therapy to help them build a stronger support system.\n\nPotential Challenges in Therapy:\nJamie's skepticism towards therapy and belief that they should be able to overcome their struggles independently may pose challenges in engaging them in the therapeutic process. Additionally, their severe symptoms and lack of motivation may make it difficult for them to consistently attend sessions and complete homework assignments.\n\nTreatment Goals:\n1. Develop a consistent sleep schedule and improve sleep hygiene to reduce insomnia symptoms.\n2. Reengage with previously enjoyed hobbies, such as hiking, dancing, and cooking, to foster a sense of purpose and enjoyment in life.\n3. Challenge negative thought patterns related to worthlessness and hopelessness and develop a more balanced and compassionate view of themselves.\n4. Utilize neighborhood connections to build a stronger support system and increase social engagement.\n5. Explore the impact of identity struggles, infertility, and job loss on Jamie's mental health and develop coping strategies to address these underlying issues.\n6. Address emotional eating and develop healthier coping mechanisms for managing difficult emotions.\n\nCultural, Religious, or Personal Beliefs:\nJamie does not identify with any particular religion but holds a strong belief in the power of nature and the importance of living in harmony with the environment. This belief may be incorporated into their treatment plan by encouraging outdoor activities and mindfulness practices in nature.",
  "characteristics": {
    "Age": "66+",
    "Gender": "Non-binary",
    "Ethnicity": "Caucasian",
    "Education": "Some College",
    "Occupation": "Unemployed",
    "Symptom_Severity": "Severe",
    "Engagement_Level": "Medium",
    "Life_Events": [
      "Identity crisis",
      "Infertility or pregnancy loss",
      "Recent job loss"
    ],
    "Family_Background": "Only child",
    "Hobbies_Interests": [
      "Hiking or camping",
      "Dancing",
      "Singing",
      "Yoga or meditation",
      "Cooking or baking"
    ],
    "Social_Support": "Neighborhood connections",
    "Personality_Traits": [
      "Resilient",
      "Extroverted"
    ],
    "Coping_Mechanisms": [
      "Journaling",
      "Emotional eating",
      "Excessive sleeping"
    ]
  }
}