{
  "profile": "Patient Profile: Alex M.\n\nBackstory:\nAlex, a 31-year-old Middle Eastern transgender individual, grew up in a supportive LGBTQ+ family. Despite the accepting home environment, Alex faced discrimination and bullying throughout school, leading to a lifelong struggle with self-acceptance and impulsive decision-making. After graduating high school, Alex attended college but dropped out after two years, feeling lost and unsure about their future. At 28, Alex made a significant career change, leaving a retail job to work in an office setting, hoping for a fresh start. However, the lack of fulfillment in their new role and the pressure to conform to societal norms exacerbated Alex's feelings of isolation and sadness.\n\nCurrent Life Situation:\nAlex currently lives alone in a small apartment in a diverse neighborhood. Despite having a stable white-collar job, Alex finds the work unfulfilling and struggles to form meaningful connections with colleagues. Outside of work, Alex engages in yoga and meditation, which provide temporary relief from their emotional distress. On weekends, Alex often travels to nearby towns for photography excursions, seeking solace in nature and creative expression. However, Alex's impulsive spending on these trips has led to financial stress, further contributing to their depression.\n\nDepressive Symptoms and Impact:\nAlex experiences mild depressive symptoms, including persistent feelings of sadness, low energy, and difficulty concentrating at work. These symptoms have led to decreased productivity and increased absenteeism, putting Alex's job at risk. Alex's depression has also affected their relationships, causing them to withdraw from friends and family members, including their supportive LGBTQ+ family. Alex often cancels plans at the last minute and has stopped attending local community events, despite their love for photography and travel.\n\nOnset and Progression of Depression:\nAlex's depression first emerged during college, following years of bullying and internalized transphobia. The lack of direction and sense of belonging exacerbated Alex's feelings of worthlessness. The recent career change, while initially promising, has led to increased stress and a sense of failure, as Alex feels unable to find fulfillment or build a meaningful career.\n\nTreatment History and Attitude Towards Therapy:\nAlex has never sought professional help for their depression, believing that they should be able to cope on their own. However, Alex's neighbor, a therapist, has gently encouraged them to consider therapy, sensing Alex's struggles. Alex is hesitant but open to the idea, recognizing that their current coping mechanisms are insufficient.\n\nCoping Mechanisms and Effectiveness:\nAlex engages in both healthy and unhealthy coping mechanisms. Yoga and meditation provide temporary relief, helping Alex feel more grounded and present. However, Alex also resorts to self-harm during particularly difficult moments, a behavior they feel ashamed of and hide from others. Exercise, while beneficial for their mental health, is often sporadic due to Alex's low motivation and energy levels.\n\nSocial Support System:\nDespite withdrawing from many relationships, Alex maintains connections with their neighbors, who have become a source of support. Alex's neighbor, the therapist, has been particularly understanding and encouraging. However, Alex struggles to fully utilize this support, fearing judgment and vulnerability.\n\nPersonal Strengths and Resilience Factors:\nDespite their struggles, Alex possesses a resilient spirit, having overcome significant challenges throughout their life. Their love for photography and travel demonstrates a sense of adventure and creativity, which could be harnessed in therapy. Alex's impulsive nature, while sometimes problematic, also reflects a willingness to take risks and embrace change.\n\nPotential Challenges in Therapy:\nAlex's impulsivity and fear of vulnerability may present challenges in therapy. They may struggle to commit to regular sessions or engage in deep emotional work. Alex's internalized transphobia and shame around their self-harm behaviors may also hinder their ability to fully open up to a therapist.\n\nTreatment Goals:\n1. Develop healthier coping mechanisms to replace self-harm and impulsive spending.\n2. Improve self-acceptance and work through internalized transphobia.\n3. Identify and pursue a more fulfilling career path that aligns with Alex's values and interests.\n4. Strengthen relationships with friends, family, and colleagues, learning to communicate needs and set boundaries.\n5. Engage in regular physical activity and mindfulness practices to manage depressive symptoms.\n6. Explore creative outlets, such as photography, as a means of self-expression and emotional processing.\n\nCultural, Religious, or Personal Beliefs:\nAlex's Middle Eastern heritage and LGBTQ+ identity are both integral to their sense of self. While Alex's family is accepting, they have faced rejection and discrimination from the broader Middle Eastern community, contributing to their feelings of isolation. Alex does not adhere to any particular religion but finds solace in nature and creative pursuits, which could be incorporated into their therapy experience.",
  "characteristics": {
    "Age": "26-35",
    "Gender": "Transgender",
    "Ethnicity": "Middle Eastern",
    "Education": "Some College",
    "Occupation": "White-collar worker",
    "Symptom_Severity": "Mild",
    "Engagement_Level": "Low",
    "Life_Events": [
      "Career change"
    ],
    "Family_Background": "LGBTQ+ family",
    "Hobbies_Interests": [
      "Yoga or meditation",
      "Traveling",
      "Photography"
    ],
    "Social_Support": "Neighborhood connections",
    "Personality_Traits": [
      "Impulsive",
      "Resilient"
    ],
    "Coping_Mechanisms": [
      "Self-harm",
      "Exercise"
    ]
  }
}