{
  "profile": "Patient Profile: Jian Chen\n\nBackstory:\nJian Chen, a 24-year-old East Asian male, immigrated to the United States three years ago to pursue a doctoral degree in computer science. Coming from a family with a history of mental illness, Jian faced significant challenges adapting to a new culture while dealing with the pressure of his academic pursuits. Despite his resilience and analytical nature, Jian found himself struggling to cope with the cultural adjustment and the high expectations placed upon him by his family.\n\nCurrent Life Situation:\nAfter completing his doctoral degree, Jian has been unemployed for the past six months, struggling to find a job in his field. He lives alone in a small apartment, spending most of his time playing video games or engaging in photography, his two main hobbies. Jian's social circle is limited, primarily consisting of a veterans support group he joined after a brief stint in the military during his undergraduate years. He has difficulty maintaining close relationships and often feels isolated and disconnected from those around him.\n\nDepressive Symptoms and Impact:\nJian experiences mild symptoms of depression, which have been impacting his daily life. He often feels a sense of hopelessness and lack of motivation, struggling to find the energy to engage in job search activities or pursue his hobbies. Jian's sleep patterns are disrupted, and he frequently turns to emotional eating and substance use to cope with his negative emotions. His impulsive nature has led to a cycle of short-lived bursts of motivation followed by longer periods of inactivity and self-doubt.\n\nOnset and Progression:\nJian's depressive symptoms first emerged during his second year of graduate school, shortly after his arrival in the United States. The combination of cultural adjustment, academic pressure, and a lack of social support contributed to his deteriorating mental health. As time progressed, Jian's symptoms intensified, exacerbated by his unemployment and feelings of isolation.\n\nPrevious Treatment History:\nJian has not previously sought professional help for his depression. His cautious nature and cultural background have made him hesitant to engage in therapy, as he believes he should be able to overcome his struggles independently. However, his involvement in the veterans support group has exposed him to the potential benefits of seeking help, and he is slowly becoming more open to the idea of therapy.\n\nCoping Mechanisms:\nJian's primary coping mechanisms include substance use, emotional eating, and creative expression through photography. While these strategies provide temporary relief, they do not address the underlying causes of his depression. His analytical nature allows him to recognize the ineffectiveness of these coping mechanisms, but he struggles to find healthier alternatives.\n\nSocial Support:\nJian's social support system is limited, with the veterans support group being his primary source of connection. He attends meetings sporadically but has difficulty opening up and forming close relationships with other members. Jian's family, although supportive, lives in his home country and is not fully aware of the extent of his struggles.\n\nStrengths and Resilience:\nDespite his challenges, Jian possesses several strengths and resilience factors. His intelligence, analytical skills, and determination have enabled him to complete his doctoral degree in a foreign country. Jian's interest in photography provides him with a creative outlet and a means of self-expression. His involvement in the veterans support group demonstrates a willingness to seek help and connect with others who have faced similar challenges.\n\nPotential Challenges in Therapy:\nJian's cultural background and family history of mental illness may contribute to feelings of shame or stigma surrounding therapy. His impulsive nature and cautious approach to seeking help may also present challenges in engaging and maintaining consistent participation in therapy.\n\nTreatment Goals:\n1. Develop healthier coping mechanisms to replace substance use and emotional eating.\n2. Improve sleep hygiene and establish a consistent daily routine.\n3. Increase social engagement and build a stronger support network.\n4. Explore career options and develop a plan for re-entering the workforce.\n5. Address feelings of isolation and disconnection by fostering a sense of belonging and purpose.\n\nCultural and Personal Beliefs:\nJian's East Asian cultural background emphasizes the importance of academic and professional success, contributing to the pressure he feels to excel in his field. He may also hold traditional beliefs about mental health, viewing depression as a sign of weakness or a lack of willpower. These cultural and personal beliefs may influence his experience of depression and his approach to treatment.",
  "characteristics": {
    "Age": "18-25",
    "Gender": "Male",
    "Ethnicity": "East Asian",
    "Education": "Doctoral Degree",
    "Occupation": "Unemployed",
    "Symptom_Severity": "Mild",
    "Engagement_Level": "Low",
    "Life_Events": [
      "Cultural adjustment (e.g., immigration)"
    ],
    "Family_Background": "Family history of mental illness",
    "Hobbies_Interests": [
      "Photography",
      "Video games"
    ],
    "Social_Support": "Veterans support group",
    "Personality_Traits": [
      "Impulsive",
      "Resilient",
      "Cautious",
      "Analytical"
    ],
    "Coping_Mechanisms": [
      "Substance use",
      "Emotional eating",
      "Creative expression"
    ]
  }
}