{
  "profile": "Patient Profile: Dr. Jin-Soo Park\n\nBackstory:\nDr. Jin-Soo Park, a 42-year-old East Asian male, grew up as an only child in a highly achieving family. His parents, both successful academics, instilled in him a strong work ethic and a drive for perfection. Jin-Soo excelled in his studies, eventually earning a doctoral degree in computer science. He built a successful career in a prestigious tech company in Seoul, where he was known for his analytical mind and laid-back demeanor.\n\nHowever, Jin-Soo's life took a turn when he experienced a traumatic accident while on a business trip. This event, coupled with mounting workplace stress and burnout, led him to make the difficult decision to leave his job and move to a new city, seeking a fresh start. Jin-Soo hoped that this change would help him recover from his trauma and find a better work-life balance.\n\nCurrent Life Situation:\nJin-Soo has been unemployed for the past six months, struggling to find a new job that aligns with his skills and values. He has been living off his savings, which has added financial stress to his situation. Jin-Soo's move to a new city has left him feeling isolated, as he has not yet established a strong social network. He spends most of his days at home, reading and tending to his small garden, which has become his sanctuary.\n\nDepressive Symptoms and Impact:\nJin-Soo has been experiencing mild symptoms of depression, including persistent feelings of sadness, low energy, difficulty concentrating, and a loss of interest in activities he once enjoyed, such as dancing and collecting vintage computers. His perfectionism has turned into self-criticism, and he often finds himself avoiding social interactions and job applications due to fear of failure. Jin-Soo's low engagement in therapy and his tendency to mask his emotions with humor or occasional outbursts of anger have made it difficult for him to address his depression effectively.\n\nOnset and Progression of Depression:\nJin-Soo's depression began shortly after his traumatic accident, which left him with physical injuries and emotional scars. The workplace stress and burnout he experienced prior to the accident likely made him more vulnerable to developing depression. His decision to leave his job and move to a new city, while intended to improve his well-being, has instead exacerbated his feelings of isolation and hopelessness.\n\nPrevious Treatment History:\nJin-Soo has not sought professional help for his depression before, as he believes that he should be able to overcome his challenges on his own. His cultural background and family upbringing have instilled in him a sense of self-reliance and a stigma around mental health issues. However, Jin-Soo has recently become more open to the idea of therapy, recognizing that his current coping mechanisms are not sufficient.\n\nCoping Mechanisms and Effectiveness:\nJin-Soo has been relying on a combination of coping mechanisms, including humor, avoidance, and occasional anger or aggression. While these strategies may provide temporary relief, they have not addressed the root causes of his depression. Jin-Soo's interest in yoga and meditation has helped him manage his stress to some extent, but he struggles to maintain a consistent practice.\n\nSocial Support System:\nDespite his isolation, Jin-Soo has been active in a local community gardening group, where he has found a sense of belonging and purpose. This group has become his primary source of social support, as he feels understood and valued by his fellow gardeners. However, Jin-Soo has not shared his struggles with depression with anyone in the group, fearing judgment and rejection.\n\nPersonal Strengths and Resilience Factors:\nJin-Soo's analytical mind, laid-back demeanor, and ability to find humor in difficult situations are personal strengths that can be leveraged in therapy. His interest in gardening and his active involvement in the community group demonstrate his capacity for resilience and his desire to connect with others. Jin-Soo's high level of education and his past success in his career also suggest a strong foundation of skills and resources that can support his recovery.\n\nPotential Challenges in Therapy:\nJin-Soo's perfectionism, avoidance, and reluctance to seek help may pose challenges in therapy. His cultural background and family upbringing may also contribute to a sense of shame or stigma around mental health issues, making it difficult for him to fully engage in the therapeutic process. Additionally, Jin-Soo's tendency to mask his emotions with humor or anger may make it challenging for him to develop the self-awareness and emotional regulation skills necessary for recovery.\n\nPersonalized Treatment Goals:\n1. Develop healthy coping mechanisms to replace perfectionism, avoidance, and anger.\n2. Improve self-awareness and emotional regulation skills.\n3. Increase social connections and support, both within and outside of the community gardening group.\n4. Explore and address the impact of cultural and family beliefs on Jin-Soo's mental health and help-seeking behavior.\n5. Collaborate with Jin-Soo to identify meaningful career goals and develop a plan for re-entering the workforce in a way that aligns with his values and supports his well-being.\n6. Engage Jin-Soo in activities that promote a sense of purpose and accomplishment, such as volunteering or mentoring others in his field of expertise.\n\nCultural, Religious, or Personal Beliefs:\nJin-Soo's East Asian cultural background and his family's emphasis on achievement and self-reliance may influence his experience of depression and his approach to treatment. He may feel a sense of shame or failure associated with his current situation, and he may be reluctant to discuss his mental health struggles openly. Jin-Soo's spiritual beliefs, which are rooted in Buddhism, may also shape his understanding of suffering and his approach to coping with adversity. In therapy, it will be important to acknowledge and respect these cultural and personal beliefs while helping Jin-Soo develop a more compassionate and accepting relationship with himself.",
  "characteristics": {
    "Age": "36-45",
    "Gender": "Male",
    "Ethnicity": "East Asian",
    "Education": "Doctoral Degree",
    "Occupation": "Unemployed",
    "Symptom_Severity": "Mild",
    "Engagement_Level": "Low",
    "Life_Events": [
      "Workplace stress or burnout",
      "Moving to a new city",
      "Traumatic event (e.g., accident, assault)"
    ],
    "Family_Background": "Only child",
    "Hobbies_Interests": [
      "Reading",
      "Yoga or meditation",
      "Gardening",
      "Dancing",
      "Collecting (specify)"
    ],
    "Social_Support": "Active in community groups",
    "Personality_Traits": [
      "Analytical",
      "Laid-back"
    ],
    "Coping_Mechanisms": [
      "Perfectionism",
      "Humor or laughter",
      "Anger or aggression",
      "Avoidance"
    ]
  }
}