{
  "profile": "Patient Profile: Amir Hossein\n\nBackstory:\nAmir Hossein, a 42-year-old Middle Eastern man, has faced numerous challenges throughout his life. Growing up in a family affected by divorce, Amir struggled to find stability and support. Despite these difficulties, he managed to complete high school and secure a white-collar job in a local company.\n\nAmir's passion for photography and collecting vintage cameras provided him with a creative outlet and a sense of purpose. He also found solace in caring for his beloved pet dog, a loyal companion who offered unconditional love and support.\n\nHowever, Amir's life took a turn for the worse when he experienced financial difficulties due to a company downsizing. The stress of making ends meet led him to substance abuse, which quickly spiraled out of control. With the help of a veterans support group, Amir managed to overcome his addiction, but the experience left him emotionally drained and vulnerable.\n\nCurrent Life Situation:\nAmir currently lives alone in a small apartment, struggling to make ends meet. His financial difficulties persist, causing him significant stress and anxiety. Despite his best efforts to maintain his white-collar job, Amir finds it increasingly challenging to focus and perform at work due to his severe depressive symptoms.\n\nAmir's relationships have suffered due to his depression and past substance abuse. He has become more reserved and withdrawn, finding it difficult to connect with others and maintain close friendships. His family, already distant due to the divorce, provides little support or understanding of his struggles.\n\nDepressive Symptoms and Impact:\nAmir experiences severe symptoms of depression, including persistent feelings of sadness, hopelessness, and worthlessness. He struggles with insomnia, finding it difficult to fall and stay asleep, which exacerbates his fatigue and lack of energy during the day. Amir's appetite has decreased significantly, leading to unintentional weight loss and further impacting his overall health.\n\nAmir's depression has greatly affected his ability to function in his daily life. He finds it challenging to concentrate at work, leading to decreased productivity and increased anxiety about job security. His hobbies, once a source of joy and relaxation, no longer provide the same level of fulfillment or motivation.\n\nOnset and Progression of Depression:\nAmir's depression first emerged during his adolescence, following his parents' divorce. The instability and emotional turmoil of his family life left him feeling abandoned and helpless. However, it was not until his recent financial difficulties and substance abuse recovery that his depressive symptoms escalated to their current severe state.\n\nPrevious Treatment History:\nAmir has never sought professional help for his depression, primarily due to the stigma surrounding mental health in his culture and his own belief that he should be able to overcome his struggles independently. He has relied on the support of his veterans group, but has not engaged in any formal therapy or treatment.\n\nCoping Mechanisms and Effectiveness:\nAmir's primary coping mechanisms have been perfectionism and substance use. He strives to maintain control and high standards in his work and personal life, hoping to counteract his feelings of worthlessness and inadequacy. However, this perfectionism often leads to increased stress and self-criticism.\n\nHis history of substance abuse provided temporary relief from his emotional pain, but ultimately exacerbated his depression and led to further consequences.\n\nSocial Support System:\nAmir's main source of social support is his veterans group, which has been instrumental in his substance abuse recovery. The group provides a sense of camaraderie and understanding, as many members have faced similar challenges. However, Amir struggles to openly discuss his depression within the group, fearing judgment and a lack of understanding.\n\nPersonal Strengths and Resilience Factors:\nDespite his struggles, Amir possesses several strengths and resilience factors. His analytical mind allows him to problem-solve and think critically, even in the face of adversity. His passion for photography and collecting provides him with a creative outlet and a sense of accomplishment. Amir's love for his pet dog demonstrates his capacity for empathy, care, and unconditional love.\n\nPotential Challenges in Therapy:\nAmir's cultural background and personal beliefs may present challenges in therapy. The stigma surrounding mental health in his community may make it difficult for him to openly discuss his struggles and engage in treatment. His perfectionism and self-critical nature may also hinder his ability to accept support and make progress in therapy.\n\nAdditionally, Amir's reserved and pessimistic personality traits may make it challenging for him to trust and open up to a therapist. Establishing a strong therapeutic alliance and creating a safe, non-judgmental space will be crucial in helping Amir feel comfortable and engaged in the therapeutic process.\n\nPersonalized Goals for Treatment:\n1. Develop healthy coping mechanisms to replace perfectionism and substance use.\n2. Improve sleep hygiene and establish a consistent sleep schedule to alleviate insomnia and fatigue.\n3. Increase engagement in photography and collecting hobbies to foster a sense of purpose and accomplishment.\n4. Strengthen social support system by openly discussing depression with trusted individuals and exploring new support groups or communities.\n5. Challenge negative thought patterns and self-critical beliefs to improve self-esteem and reduce feelings of worthlessness.\n6. Address financial difficulties through budgeting, financial planning, and exploring potential career advancement opportunities.\n7. Process and heal from family-related trauma and improve family relationships through open communication and boundary setting.\n8. Develop a self-care routine that incorporates physical exercise, healthy eating, and stress-reducing activities.\n9. Explore cultural and personal beliefs surrounding mental health and work to reduce self-stigma and increase acceptance of treatment.\n10. Cultivate a sense of hope and optimism for the future by celebrating small victories and focusing on personal growth and resilience.\n\nCultural, Religious, and Personal Beliefs:\nAmir's Middle Eastern background plays a significant role in his beliefs and attitudes towards mental health. In his culture, mental health issues are often stigmatized and viewed as personal weaknesses rather than legitimate medical concerns. This stigma has contributed to Amir's reluctance to seek help and his belief that he should be able to overcome his struggles independently.\n\nReligiously, Amir identifies as Muslim, although he does not actively practice. His faith has provided him with a sense of community and cultural identity, but he struggles to reconcile his beliefs with his experiences of depression and substance abuse.\n\nAmir's personal beliefs center around the importance of self-reliance, hard work, and perseverance. He prides himself on his ability to overcome challenges independently, which has made it difficult for him to accept help and support from others. These beliefs also contribute to his perfectionism and self-critical nature, as he holds himself to high standards and fears the judgment of others.\n\nIn therapy, it will be essential to explore and address these cultural, religious, and personal beliefs in a sensitive and respectful manner. By acknowledging and validating Amir's experiences and beliefs, the therapist can help him develop a more compassionate and understanding view of himself and his struggles. Incorporating elements of his cultural identity and personal values into the therapeutic process may also help Amir feel more comfortable and engaged in treatment.",
  "characteristics": {
    "Age": "36-45",
    "Gender": "Male",
    "Ethnicity": "Middle Eastern",
    "Education": "High School",
    "Occupation": "White-collar worker",
    "Symptom_Severity": "Severe",
    "Engagement_Level": "High",
    "Life_Events": [
      "Financial difficulties",
      "Substance abuse recovery"
    ],
    "Family_Background": "Family affected by divorce or separation",
    "Hobbies_Interests": [
      "Photography",
      "Collecting (specify)",
      "Animal care or pet ownership"
    ],
    "Social_Support": "Veterans support group",
    "Personality_Traits": [
      "Analytical",
      "Pessimistic",
      "Easy-going",
      "Reserved"
    ],
    "Coping_Mechanisms": [
      "Perfectionism",
      "Substance use"
    ]
  }
}