{
  "profile": "Patient Profile: Emilio Sol\u00eds (They/Them)\n\nBackstory:\nEmilio Sol\u00eds, a 42-year-old Hispanic individual, was born and raised in a close-knit blended family in a small town in New Mexico. Emilio's parents divorced when they were young, and both remarried, creating a complex family dynamic. Despite the challenges, Emilio found solace in their love for the outdoors, often exploring the nearby mountains with their step-siblings.\n\nEmilio's passion for photography developed in their teenage years, capturing the beauty of the landscapes they encountered during their hikes. After graduating high school, Emilio decided to pursue a degree in environmental science, hoping to combine their love for nature with a meaningful career.\n\nHowever, during their second year of college, Emilio experienced an identity crisis, questioning their gender identity and feeling disconnected from their cultural roots. They took a break from their studies to work and save money, eventually moving to a larger city to attend a different college.\n\nIn the new city, Emilio struggled to make friends and felt overwhelmed by the fast-paced lifestyle. They began working part-time at an animal shelter, finding comfort in caring for the animals and connecting with like-minded colleagues.\n\nCurrent Life Situation:\nEmilio is currently a part-time student, pursuing their environmental science degree while working at the animal shelter. They live alone in a small apartment and struggle to balance their work, studies, and personal life. Emilio often feels isolated, as they have not yet found a strong support system in the new city.\n\nDepressive Symptoms and Impact:\nEmilio experiences mild depressive symptoms, including persistent feelings of sadness, lack of motivation, and difficulty concentrating on their studies. They often feel disconnected from their emotions and struggle to express their feelings to others. Emilio's symptoms have led to a decline in their academic performance and a sense of hopelessness about their future.\n\nOnset and Progression of Depression:\nEmilio's depressive symptoms first emerged during their identity crisis in college. The move to a new city exacerbated these feelings, as they grappled with the loss of their support system and the challenges of adapting to a new environment. Emilio's workplace stress and the pressure to succeed academically have further contributed to their depression.\n\nPrevious Treatment History:\nEmilio has not previously sought professional help for their depression, as they were taught to be self-reliant and to cope with their problems independently. However, they have recently begun to recognize the impact of their symptoms on their daily life and are now more open to seeking therapy.\n\nCoping Mechanisms and Effectiveness:\nEmilio's primary coping mechanisms include excessive sleeping, problem-solving, and journaling. While these strategies provide temporary relief, they do not address the root causes of their depression. Emilio's ambitious and optimistic nature helps them maintain a sense of hope, but their reserved personality makes it challenging to reach out for support.\n\nSocial Support System:\nEmilio's primary source of social support is their work colleagues at the animal shelter. They find solace in the shared passion for animal care and the non-judgmental atmosphere of the workplace. However, Emilio struggles to form deeper connections and often feels like an outsider in social situations.\n\nPersonal Strengths and Resources:\nDespite their challenges, Emilio possesses several strengths and resilience factors. Their love for nature and photography provides a creative outlet and a source of inner peace. Emilio's extroverted personality allows them to connect with others when they feel comfortable, and their problem-solving skills help them navigate difficult situations.\n\nPotential Challenges in Therapy:\nEmilio's reserved nature and difficulty expressing emotions may present challenges in therapy. They may struggle to open up to their therapist and fully engage in the therapeutic process. Additionally, Emilio's cultural background and family dynamics may influence their perspectives on mental health and seeking help.\n\nTreatment Goals:\n1. Develop healthy coping mechanisms to manage depressive symptoms and reduce reliance on excessive sleep.\n2. Improve emotional regulation and expression, allowing Emilio to better communicate their feelings and needs.\n3. Explore and process Emilio's identity crisis, helping them develop a stronger sense of self and connection to their cultural heritage.\n4. Enhance Emilio's social support system by encouraging them to engage in hobbies and activities that align with their interests, such as joining a hiking or photography club.\n5. Address workplace stress and burnout by developing strategies for self-care and setting healthy boundaries.\n6. Support Emilio in creating a balanced lifestyle that incorporates their academic pursuits, work responsibilities, and personal well-being.\n\nCultural and Personal Beliefs:\nEmilio's Hispanic heritage and blended family background have shaped their values and beliefs. They place a strong emphasis on family, community, and resilience. However, Emilio also struggles with feelings of guilt and shame surrounding their mental health, as they were taught to be strong and self-reliant. In therapy, it will be essential to acknowledge and respect Emilio's cultural background while helping them develop a healthier perspective on mental health and self-care.",
  "characteristics": {
    "Age": "36-45",
    "Gender": "Other",
    "Ethnicity": "Hispanic",
    "Education": "Some College",
    "Occupation": "Student",
    "Symptom_Severity": "Mild",
    "Engagement_Level": "Medium",
    "Life_Events": [
      "Identity crisis",
      "Workplace stress or burnout",
      "Moving to a new city"
    ],
    "Family_Background": "Blended family",
    "Hobbies_Interests": [
      "Hiking or camping",
      "Animal care or pet ownership",
      "Photography",
      "Yoga or meditation"
    ],
    "Social_Support": "Work colleagues",
    "Personality_Traits": [
      "Ambitious",
      "Reserved",
      "Extroverted",
      "Optimistic"
    ],
    "Coping_Mechanisms": [
      "Excessive sleeping",
      "Problem-solving",
      "Journaling"
    ]
  }
}