{
  "profile": "Patient Profile: Emilio Rodriguez\n\nBackstory:\nEmilio Rodriguez, a 68-year-old Hispanic transgender man, was born into a high-achieving family in a small town in Texas. From a young age, Emilio felt the pressure to excel academically and make his family proud. He graduated with honors from a prestigious university and earned a Master's degree in Linguistics.\n\nEmilio's life took a dramatic turn when he enlisted in the military and was deployed overseas. During his service, he experienced traumatic events that left him with deep emotional scars. Upon returning home, Emilio struggled to readjust to civilian life and faced the devastating loss of his partner, who had been his main source of support.\n\nCurrent Life Situation:\nEmilio currently lives alone in a small apartment, having been unemployed for the past two years. He spends most of his days taking care of his two rescue dogs, whom he considers his closest companions. Emilio's limited social interactions are primarily with members of his local LGBTQ+ friendly church, where he finds solace and a sense of belonging.\n\nDespite his extroverted nature, Emilio's impulsive behavior and anger outbursts have strained his relationships with family and friends. He often copes with his emotions by engaging in intense exercise routines, retail therapy, or learning new languages through online courses.\n\nDepressive Symptoms and Impact:\nEmilio's severe depression manifests through persistent feelings of worthlessness, guilt, and hopelessness. He experiences insomnia, loss of appetite, and a lack of interest in activities he once enjoyed, such as reading and attending social events. Emilio's depression has made it difficult for him to maintain steady employment and has led to financial instability.\n\nOnset and Progression of Depression:\nEmilio's depression began during his military service, following a series of traumatic experiences. The loss of his partner upon returning home exacerbated his symptoms, leading to a steady decline in his mental health. The pressure to succeed and the feeling of not living up to his family's expectations have further contributed to his depressive state.\n\nPrevious Treatment History:\nEmilio has previously sought therapy but struggled to find a provider who could understand and address his unique needs as a transgender veteran. His impulsive nature and difficulty trusting others have made it challenging for him to engage in therapy consistently.\n\nCoping Mechanisms:\nEmilio's coping mechanisms include exercise, which provides temporary relief from his depressive symptoms. However, his impulsive spending and anger outbursts often lead to feelings of guilt and worsen his overall mental state. Learning languages and caring for his dogs offer him a sense of purpose and distraction from his negative thoughts.\n\nSocial Support System:\nEmilio's primary source of social support is his religious community, which has been accepting of his gender identity. He attends weekly services and participates in volunteer work organized by the church. However, he struggles to form deep connections with others due to his fear of rejection and past experiences of discrimination.\n\nStrengths and Resilience Factors:\nDespite his challenges, Emilio possesses several strengths, including his high level of engagement in therapy, his love for animals, and his passion for learning. His extroverted nature allows him to connect with others easily when he feels comfortable, and his resilience is evident in his ability to cope with significant loss and trauma.\n\nPotential Challenges in Therapy:\nEmilio's impulsivity and difficulty trusting others may pose challenges in therapy. His past experiences of discrimination and the pressure to succeed may also impact his ability to open up and fully engage in the therapeutic process.\n\nTreatment Goals:\n1. Develop healthy coping mechanisms to manage depressive symptoms and impulsive behaviors.\n2. Improve sleep quality and appetite through a combination of therapy and lifestyle changes.\n3. Establish a stable support network outside of his religious community, focusing on building meaningful relationships.\n4. Explore career options that align with his interests and provide a sense of purpose and financial stability.\n5. Address unresolved trauma and grief related to his military service and the loss of his partner.\n6. Work on improving his relationship with his family and finding ways to communicate his needs effectively.\n\nCultural and Religious Beliefs:\nEmilio's Hispanic heritage and religious beliefs play a significant role in his life. He often struggles with feelings of guilt and the belief that his depression is a sign of weakness or a lack of faith. Incorporating his spiritual beliefs into therapy and acknowledging the cultural pressure to succeed will be crucial in addressing his depression.",
  "characteristics": {
    "Age": "66+",
    "Gender": "Transgender",
    "Ethnicity": "Hispanic",
    "Education": "Master's Degree",
    "Occupation": "Unemployed",
    "Symptom_Severity": "Severe",
    "Engagement_Level": "High",
    "Life_Events": [
      "Death of a loved one",
      "Military service or deployment"
    ],
    "Family_Background": "High-achieving family with pressure to succeed",
    "Hobbies_Interests": [
      "Animal care or pet ownership",
      "Learning languages",
      "Reading"
    ],
    "Social_Support": "Religious or spiritual community",
    "Personality_Traits": [
      "Impulsive",
      "Extroverted"
    ],
    "Coping_Mechanisms": [
      "Exercise",
      "Anger or aggression",
      "Retail therapy"
    ]
  }
}