{
  "profile": "Patient Profile: Jamie Thompson\n\nBackstory:\nJamie Thompson, a 52-year-old non-binary individual of African American descent, grew up in a close-knit, multi-generational household in a small town in the southern United States. Jamie's family placed a strong emphasis on education, and after high school, Jamie attended a local community college, studying liberal arts. However, due to financial constraints and family obligations, Jamie had to leave college after two years and take up a blue-collar job at a local factory to support the family.\n\nTwo years ago, Jamie made the difficult decision to move to a new city in search of better job prospects. Although the move provided financial stability, Jamie struggled to adapt to the new environment, missing the strong sense of community and the close relationships with family and friends back home.\n\nCurrent Life Situation:\nJamie works long hours at the factory, often taking on overtime shifts to make ends meet. The job is physically demanding and leaves little time or energy for socializing or pursuing hobbies. Jamie lives alone in a small apartment and has found it challenging to build a new social network in the city. Although Jamie has a strong network of friends from back home, the distance makes it difficult to maintain regular contact.\n\nJamie's daily life is marked by a sense of isolation and loneliness, compounded by the lack of a romantic partner and the absence of a strong support system in the new city. Jamie often feels disconnected from others and struggles to find joy in previously enjoyed activities, such as singing, learning languages, and playing board games.\n\nDepressive Symptoms and Impact:\nJamie's depressive symptoms have been moderate but persistent over the past year. Jamie often experiences feelings of sadness, hopelessness, and a lack of motivation. These symptoms have led to a decrease in productivity at work, social withdrawal, and a diminished interest in hobbies and activities that once brought joy.\n\nJamie's sleep patterns have been disrupted, with difficulty falling asleep and frequent waking during the night. This has resulted in fatigue and a lack of energy during the day. Jamie's appetite has also been affected, with a tendency to overeat or indulge in unhealthy comfort foods.\n\nOnset and Progression of Depression:\nJamie first noticed the onset of depressive symptoms shortly after moving to the new city. The isolation and lack of social support, combined with the stress of adjusting to a new job and environment, likely triggered the initial depressive episode. Over time, the symptoms have worsened and become more persistent, affecting Jamie's overall quality of life.\n\nPrevious Treatment History:\nJamie has not sought professional help for depression in the past. A combination of factors, including a lack of awareness about mental health resources, financial concerns, and a reluctance to discuss personal struggles with others, has prevented Jamie from reaching out for support.\n\nCoping Mechanisms:\nJamie has developed a few coping mechanisms to deal with the depressive symptoms. Humor and laughter have been a way for Jamie to mask the pain and connect with others, even if superficially. Creative expression through singing and learning new languages has provided temporary relief from the emotional distress. However, Jamie's tendency to withdraw socially has further exacerbated the feelings of isolation and loneliness.\n\nSocial Support System:\nDespite the distance, Jamie maintains regular contact with a few close friends from back home. They provide emotional support and a listening ear during difficult times. However, the lack of a strong support system in the new city has made it challenging for Jamie to find consistent, in-person support.\n\nPersonal Strengths and Resilience Factors:\nJamie's adventurous spirit and willingness to take risks, as evidenced by the move to a new city, demonstrate a level of resilience and adaptability. Jamie's love for learning languages and exploring new cultures also suggests a curiosity and openness to new experiences. These strengths can be leveraged in therapy to help Jamie build a more fulfilling life in the new city.\n\nPotential Challenges in Therapy:\nJamie's cautious nature and tendency to withdraw socially may make it difficult to establish trust and open up in therapy. The financial concerns and lack of knowledge about mental health resources may also pose barriers to consistent engagement in treatment.\n\nTreatment Goals:\n1. Develop healthy coping mechanisms to manage depressive symptoms and reduce reliance on social withdrawal.\n2. Increase social connections and build a support system in the new city, possibly through joining clubs or groups related to Jamie's interests (e.g., language learning, board game clubs, or travel groups).\n3. Improve sleep hygiene and develop a consistent self-care routine to enhance overall well-being.\n4. Explore ways to find fulfillment and meaning in life, both within and outside of work.\n5. Address any unresolved feelings of grief or loss related to the move and the changes in family dynamics.\n\nCultural and Personal Beliefs:\nAs an African American individual, Jamie may have experienced systemic barriers and discrimination that have contributed to feelings of isolation and hopelessness. Acknowledging and addressing these experiences in therapy will be crucial. Additionally, Jamie's strong family values and the importance placed on education and community may influence their approach to treatment and the desire to find a sense of belonging in the new city.",
  "characteristics": {
    "Age": "46-55",
    "Gender": "Non-binary",
    "Ethnicity": "African American",
    "Education": "Some College",
    "Occupation": "Blue-collar worker",
    "Symptom_Severity": "Moderate",
    "Engagement_Level": "Low",
    "Life_Events": [
      "Moving to a new city"
    ],
    "Family_Background": "Multi-generational household",
    "Hobbies_Interests": [
      "Singing",
      "Learning languages",
      "Board games",
      "Traveling"
    ],
    "Social_Support": "Strong network of friends",
    "Personality_Traits": [
      "Cautious",
      "Adventurous"
    ],
    "Coping_Mechanisms": [
      "Humor or laughter",
      "Social withdrawal",
      "Creative expression"
    ]
  }
}