{
  "profile": "Patient Profile: Amira Qadri\n\nBackstory:\nAmira Qadri, a 62-year-old Middle Eastern woman, was born and raised in a tight-knit single-parent household in Beirut, Lebanon. Her father, a university professor, instilled in her a love for learning and critical thinking from a young age. Despite the challenges of growing up without her mother, who passed away when Amira was just five, she excelled academically and went on to earn a bachelor's degree in Business Administration.\n\nIn her late twenties, Amira immigrated to the United States to pursue better career opportunities. She settled in Chicago, where she secured a job at a mid-sized consulting firm. Over the years, Amira worked her way up to a senior management position, known for her analytical mind and problem-solving skills. However, the demanding nature of her job and the long hours took a toll on her mental health.\n\nCurrent Life Situation:\nAmira lives alone in a cozy apartment in the suburbs of Chicago. She has never married or had children, focusing instead on her career and personal interests. Her weekdays are consumed by work, often extending into the evenings. On weekends, Amira finds solace in volunteering at a local community center, where she teaches cooking classes to underprivileged youth. She also enjoys tending to her small garden, growing herbs and vegetables for her culinary experiments.\n\nDespite her successful career and engaging hobbies, Amira has been struggling with mild depressive symptoms for the past two years. She finds it increasingly difficult to motivate herself to go to work, and her usual enthusiasm for volunteering has waned. Amira has also noticed a decline in her appetite and has trouble falling asleep at night, often lying awake for hours with racing thoughts.\n\nDepressive Symptoms and Impact:\nAmira's depressive symptoms include persistent low mood, fatigue, difficulty concentrating, and a loss of interest in activities she once enjoyed. These symptoms have made it challenging for her to perform at her usual high level at work, and she has begun to feel disconnected from her colleagues. Amira's sleep disturbances have left her feeling exhausted during the day, making it harder to engage in her hobbies and maintain her social connections.\n\nOnset and Progression of Depression:\nAmira traces the onset of her depressive symptoms to a particularly stressful period at work two years ago, when her company underwent a major restructuring. The increased workload and uncertainty about her job security triggered intense anxiety and feelings of overwhelm. Around the same time, Amira's father passed away unexpectedly, leaving her feeling emotionally adrift and exacerbating her depressive symptoms.\n\nPrevious Treatment History:\nAmira has never sought professional help for her depression, initially attributing her symptoms to work-related stress and grief over her father's death. She has a history of substance abuse, having struggled with alcohol dependence in her late thirties and early forties. With the help of a 12-step program and her strong network of friends, Amira has maintained sobriety for the past 15 years. However, she has recently found herself tempted to turn to alcohol again to cope with her depressive symptoms.\n\nCoping Mechanisms and Effectiveness:\nAmira's primary coping mechanisms include avoidance, substance use, and problem-solving. While her analytical and problem-solving skills have served her well in her professional life, she has found it challenging to apply these strategies to her emotional struggles. Amira tends to avoid confronting her feelings, preferring to distract herself with work or other activities. Her history of substance abuse also makes her vulnerable to turning to alcohol as a maladaptive coping mechanism.\n\nSocial Support System:\nDespite living alone, Amira has a strong network of friends, many of whom she met through her volunteering work and substance abuse recovery program. She has a close friend, Lina, whom she considers a confidante and source of emotional support. Amira also maintains regular contact with her extended family in Lebanon via video calls and occasional visits.\n\nPersonal Strengths and Resilience Factors:\nAmira's resilience is evident in her ability to overcome her substance abuse and build a successful career in a foreign country. Her adventurous spirit has led her to explore new hobbies and interests, such as gardening and cooking, which provide her with a sense of purpose and fulfillment. Amira's analytical mind and problem-solving skills are valuable assets that can be harnessed in therapy to develop more adaptive coping strategies.\n\nPotential Challenges in Therapy:\nAmira's tendency to avoid confronting her emotions and her history of substance abuse may present challenges in therapy. She may initially be resistant to exploring her feelings and may struggle to open up about her experiences. Additionally, her strong problem-solving skills may lead her to approach therapy with the expectation of finding quick, practical solutions, rather than engaging in a deeper exploration of her emotional world.\n\nTreatment Goals:\nAmira's treatment goals include:\n\n1. Developing healthier coping mechanisms to replace avoidance and substance use.\n2. Improving her sleep quality and establishing a consistent self-care routine.\n3. Reconnecting with her hobbies and interests, and finding ways to integrate them more fully into her life.\n4. Addressing unresolved grief related to her father's death and exploring its impact on her current emotional state.\n5. Building a more balanced relationship with her work, and setting boundaries to prevent burnout.\n\nCultural and Personal Beliefs:\nAs a Middle Eastern woman, Amira values her cultural heritage and the importance of family and community. She may feel a sense of guilt or shame around seeking help for her mental health, as mental illness is often stigmatized in her culture. Amira's Muslim faith is an essential part of her identity, and she may find comfort and guidance in her religious practices. Incorporating her cultural and spiritual beliefs into therapy could enhance her engagement and provide a framework for understanding her experiences.",
  "characteristics": {
    "Age": "56-65",
    "Gender": "Female",
    "Ethnicity": "Middle Eastern",
    "Education": "Bachelor's Degree",
    "Occupation": "White-collar worker",
    "Symptom_Severity": "Mild",
    "Engagement_Level": "High",
    "Life_Events": [
      "Workplace stress or burnout",
      "Substance abuse recovery"
    ],
    "Family_Background": "Single-parent household",
    "Hobbies_Interests": [
      "Volunteering",
      "Cooking or baking",
      "Gardening"
    ],
    "Social_Support": "Strong network of friends",
    "Personality_Traits": [
      "Resilient",
      "Analytical",
      "Adventurous"
    ],
    "Coping_Mechanisms": [
      "Avoidance",
      "Substance use",
      "Problem-solving"
    ]
  }
}