{
  "profile": "Patient Profile: Amir\n\nBackstory:\nAmir, a 24-year-old Middle Eastern transgender individual, was adopted at a young age by a loving family. Despite their support, Amir struggled with feelings of abandonment and identity issues throughout childhood and adolescence. In college, Amir excelled academically, eventually earning a doctoral degree in biochemistry. During this time, Amir began exploring their gender identity and came out as transgender to their adoptive family and close friends. Although mostly supportive, some family members struggled to understand and accept Amir's transition, causing strain in their relationships.\n\nAfter graduating, Amir moved to a new city to start a postdoctoral position but faced discrimination and transphobia in the workplace. Feeling isolated and unsupported, Amir turned to substance abuse to cope with the stress and emotional pain. After a year of struggling with addiction, Amir sought help and entered a recovery program. Now six months sober, Amir is unemployed and living with their supportive partner, Sam, who has been a stable and loving presence throughout Amir's journey.\n\nCurrent Life Situation:\nAmir is currently unemployed and struggling to find work in their field due to gaps in their resume and the stigma surrounding their addiction and gender identity. Financial stress and feelings of worthlessness have taken a toll on Amir's mental health, leading to a low engagement level in daily life. Despite this, Amir finds solace in volunteering at a local LGBTQ+ community center, where they feel accepted and valued. Amir also enjoys reading, gardening, and working on DIY projects around the house, which provide a sense of accomplishment and purpose.\n\nDepressive Symptoms and Impact:\nAmir experiences mild depressive symptoms, including feelings of sadness, low self-esteem, and a lack of motivation. These symptoms have made it difficult for Amir to engage in job searching and daily activities, leading to increased isolation and dependence on their partner. Amir's depression is also characterized by feelings of guilt and shame surrounding their addiction and the strain it has put on their relationships with their adoptive family.\n\nOnset and Progression of Depression:\nAmir's depression first emerged during college, as they grappled with their gender identity and the fear of rejection from loved ones. These feelings intensified after graduation, as Amir faced workplace discrimination and the stress of transitioning in an unsupportive environment. The onset of substance abuse temporarily masked Amir's depression, but after entering recovery, the depressive symptoms resurfaced, compounded by the challenges of maintaining sobriety and rebuilding their life.\n\nPrevious Treatment History:\nAmir has never sought professional help for their depression, largely due to the stigma surrounding mental health in their culture and the fear of further judgment. However, through their substance abuse recovery program, Amir has gained some insight into the importance of addressing mental health and is cautiously open to the idea of therapy.\n\nCoping Mechanisms and Effectiveness:\nAmir's primary coping mechanisms have been overworking and journaling. In the past, Amir would immerse themselves in work to avoid dealing with emotional pain, but this strategy is no longer effective due to their unemployment. Journaling has been a more helpful outlet for Amir, allowing them to process their thoughts and feelings in a safe and private space. However, Amir recognizes that journaling alone is not enough to fully address their depression.\n\nSocial Support System:\nAmir's primary source of support is their partner, Sam, who has been unwavering in their love and encouragement. Sam actively listens to Amir's struggles, provides emotional support, and helps Amir stay accountable in their recovery journey. Amir also finds support through their involvement in the LGBTQ+ community center, where they have made friends who understand and relate to their experiences.\n\nPersonal Strengths and Resilience Factors:\nDespite their struggles, Amir possesses several strengths and resilience factors that can be leveraged in therapy. Their laid-back personality allows them to approach challenges with a sense of calm and adaptability. Amir's creativity and optimism also enable them to find unique solutions to problems and maintain hope for the future. Additionally, Amir's strong bond with their partner and their passion for volunteering demonstrate their capacity for forming meaningful connections and contributing to their community.\n\nPotential Challenges in Therapy:\nOne potential challenge in therapy may be Amir's initial resistance to fully engaging in the process due to cultural stigma and the fear of judgment. The therapist will need to work on building trust and creating a safe, non-judgmental space for Amir to explore their thoughts and emotions. Additionally, Amir's history of overworking and tendency to minimize their own struggles may make it difficult for them to prioritize their mental health and fully commit to the therapeutic process.\n\nTreatment Goals:\n1. Develop healthy coping mechanisms for managing depressive symptoms and stress, such as mindfulness techniques and regular physical activity.\n2. Improve self-esteem and self-worth by challenging negative self-talk and identifying personal strengths and accomplishments.\n3. Establish a routine and structure to promote a sense of purpose and motivation in daily life.\n4. Rebuild relationships with adoptive family members and establish boundaries to maintain emotional well-being.\n5. Explore career options and develop a plan for reentering the workforce in a supportive and affirming environment.\n6. Address the underlying causes of substance abuse and develop strategies for maintaining long-term sobriety.\n7. Cultivate a strong support network outside of the partnership with Sam, including friends, mentors, and a therapist.\n\nCultural, Religious, or Personal Beliefs:\nAmir's Middle Eastern heritage plays a significant role in their identity and worldview. Growing up, Amir was raised with a strong emphasis on family, community, and the importance of education. However, there is also a cultural stigma surrounding mental health and addiction, which has made it difficult for Amir to seek help and openly discuss their struggles. Additionally, Amir's adoptive family is religious, and while Amir does not actively practice the faith, they still hold some of the values and beliefs instilled in them during childhood. The therapist should be sensitive to these cultural and religious factors and work with Amir to find a treatment approach that aligns with their personal beliefs and values.",
  "characteristics": {
    "Age": "18-25",
    "Gender": "Transgender",
    "Ethnicity": "Middle Eastern",
    "Education": "Doctoral Degree",
    "Occupation": "Unemployed",
    "Symptom_Severity": "Mild",
    "Engagement_Level": "Low",
    "Life_Events": [
      "Substance abuse recovery",
      "Coming out as LGBTQ+"
    ],
    "Family_Background": "Adopted or foster care background",
    "Hobbies_Interests": [
      "Volunteering",
      "Reading",
      "Gardening",
      "DIY projects"
    ],
    "Social_Support": "Supportive partner or spouse",
    "Personality_Traits": [
      "Laid-back",
      "Creative",
      "Optimistic"
    ],
    "Coping_Mechanisms": [
      "Overworking",
      "Journaling"
    ]
  }
}