{
  "profile": "Patient Profile: Jamie Doe\n\nBackstory:\nJamie Doe, a 32-year-old non-binary individual of Caucasian descent, grew up in a high-achieving family in a small suburban town. From a young age, Jamie faced immense pressure to excel academically and pursue a prestigious career. Despite their love for creative pursuits like photography and DIY projects, Jamie felt obligated to follow in their family's footsteps and focus on a more traditional path.\n\nAfter graduating high school, Jamie worked various jobs but struggled to find a fulfilling career. They often felt like a disappointment to their family, who had high expectations for their success. In their late twenties, Jamie experienced a significant setback when they were laid off from their job due to company downsizing. This event triggered feelings of worthlessness and hopelessness, leading to the onset of severe depression.\n\nCurrent Life Situation:\nCurrently, Jamie is unemployed and struggling to find the motivation to search for a new job. They spend most of their days at home, isolated from friends and family. Jamie's partner, Alex, works long hours to support them financially and tries to be emotionally supportive, but Jamie often pushes them away, feeling like a burden.\n\nJamie's daily life is a constant struggle with fatigue, lack of interest in hobbies, and feelings of guilt for not being productive. They have difficulty maintaining basic self-care, such as regular meals and hygiene, and often experience insomnia or oversleeping.\n\nDepressive Symptoms:\nJamie's depression manifests in various ways, deeply impacting their daily life:\n\n1. Persistent feelings of sadness, hopelessness, and worthlessness.\n2. Loss of interest in previously enjoyed activities, such as photography and gardening.\n3. Insomnia or hypersomnia, leading to chronic fatigue and difficulty concentrating.\n4. Changes in appetite, resulting in significant weight loss over the past few months.\n5. Recurrent thoughts of death and passive suicidal ideation, though no active plans or intent.\n\nOnset and Progression:\nJamie's depression began after their job loss, which triggered feelings of failure and inadequacy. The lack of structure and purpose in their daily life exacerbated these feelings, leading to a downward spiral. Over the past year, Jamie's depression has progressively worsened, with increased social isolation, neglect of self-care, and a growing sense of hopelessness about the future.\n\nPrevious Treatment History:\nJamie has never sought professional help for their depression, largely due to the stigma surrounding mental health in their family and community. They often minimize their struggles, believing that they should be able to overcome their depression on their own.\n\nCoping Mechanisms:\nJamie's primary coping mechanisms include journaling, substance use, and helping others. While journaling provides a temporary outlet for their emotions, substance use has become an unhealthy escape, further exacerbating their depression. Jamie finds some solace in helping others, as it gives them a sense of purpose, but often neglects their own needs in the process.\n\nSocial Support:\nJamie's partner, Alex, is their main source of support. Alex encourages Jamie to seek help and tries to be understanding, but often feels helpless in the face of Jamie's depression. Jamie has become increasingly isolated from friends and family, feeling ashamed of their situation and not wanting to burden others.\n\nStrengths and Resilience Factors:\nDespite their depression, Jamie possesses several strengths and resilience factors:\n\n1. Creativity and passion for photography and DIY projects.\n2. Empathy and a desire to help others.\n3. A supportive partner who cares about their well-being.\n4. Past experiences of overcoming challenges and adapting to new situations.\n\nPotential Challenges in Therapy:\nJamie's cautious nature and fear of judgment may make it difficult for them to open up in therapy initially. Their impulsive tendencies, particularly regarding substance use, could also pose challenges to their progress. Additionally, the pressure to meet family expectations and the stigma surrounding mental health may create internal conflicts for Jamie as they navigate treatment.\n\nTreatment Goals:\nJamie's treatment goals should focus on:\n\n1. Developing healthy coping mechanisms and reducing reliance on substance use.\n2. Reconnecting with their passions and finding a sense of purpose outside of traditional career paths.\n3. Improving self-care and daily functioning, such as establishing a consistent sleep schedule and regular meals.\n4. Enhancing communication and emotional intimacy with their partner, Alex.\n5. Challenging negative beliefs about self-worth and reframing perceptions of success and failure.\n6. Building a support network outside of their immediate family, including friends and individuals with shared interests.\n\nCultural and Personal Beliefs:\nJamie's family background and the pressure to succeed have significantly influenced their perception of mental health and their reluctance to seek help. They may also hold beliefs about the importance of self-reliance and the stigma of admitting to struggles, which could impact their engagement in therapy. Additionally, Jamie's non-binary identity may have contributed to feelings of isolation and a lack of understanding from their family and community.",
  "characteristics": {
    "Age": "26-35",
    "Gender": "Non-binary",
    "Ethnicity": "Caucasian",
    "Education": "High School",
    "Occupation": "Unemployed",
    "Symptom_Severity": "Severe",
    "Engagement_Level": "Low",
    "Life_Events": [
      "Retirement",
      "Recent job loss"
    ],
    "Family_Background": "High-achieving family with pressure to succeed",
    "Hobbies_Interests": [
      "Reading",
      "Photography",
      "DIY projects",
      "Gardening",
      "Learning languages"
    ],
    "Social_Support": "Supportive partner or spouse",
    "Personality_Traits": [
      "Cautious",
      "Impulsive"
    ],
    "Coping_Mechanisms": [
      "Journaling",
      "Substance use",
      "Helping others"
    ]
  }
}