{
  "profile": "Patient Profile: Emilio Sanchez\n\nBackstory:\nEmilio, a 24-year-old non-binary individual of Hispanic descent, grew up in a religious and conservative family in a small town. From a young age, Emilio displayed a passion for learning and an ambitious drive to succeed. They excelled academically and went on to earn a Master's degree in Psychology.\n\nAfter completing their education, Emilio made the bold decision to move to a new city in pursuit of career opportunities. However, the transition proved to be more challenging than anticipated. Despite their qualifications, Emilio struggled to find employment in their field, leading to feelings of frustration and self-doubt.\n\nCurrent Life Situation:\nCurrently, Emilio is unemployed and living alone in a small apartment in the city. They spend most of their days applying for jobs and trying to make connections in their field. Emilio's limited social circle consists mainly of acquaintances from their veterans support group, which they joined after moving to the city.\n\nEmilio's daily life is marked by a sense of isolation and lack of purpose. They struggle to maintain a regular routine and often find themselves sleeping late and neglecting self-care. Emilio's hobbies, such as cooking, singing, and writing, have taken a backseat due to their low mood and lack of motivation.\n\nDepressive Symptoms and Impact:\nEmilio's depressive symptoms have gradually worsened over the past year. They experience persistent feelings of sadness, hopelessness, and worthlessness. Emilio often criticizes themselves harshly for their perceived failures and struggles with perfectionistic tendencies.\n\nEmilio's sleep patterns are disrupted, with difficulties falling asleep and frequent awakenings during the night. They have lost interest in activities they once enjoyed, such as hiking and traveling. Emilio's appetite has decreased, leading to weight loss and fatigue.\n\nThe combination of unemployment, social isolation, and depressive symptoms has left Emilio feeling trapped and overwhelmed. They find it challenging to envision a positive future and often question their life choices.\n\nOnset and Progression:\nEmilio's depression began to emerge during their college years. The pressure to excel academically, combined with the stress of concealing their non-binary identity from their conservative family, took a toll on their mental health. However, Emilio pushed through and completed their degree, hoping that a successful career would alleviate their distress.\n\nThe move to a new city and the subsequent struggle to find employment exacerbated Emilio's depressive symptoms. The lack of structure, social support, and a sense of purpose intensified their feelings of hopelessness and worthlessness.\n\nPrevious Treatment History:\nEmilio has never sought professional help for their depression. They have a strong sense of self-reliance and believe that they should be able to overcome their struggles independently. Emilio's perfectionism also contributes to their reluctance to seek therapy, as they fear being perceived as weak or flawed.\n\nCoping Mechanisms:\nEmilio's primary coping mechanisms have been exercise and perfectionism. They engage in rigorous workout routines in an attempt to boost their mood and gain a sense of control. However, their perfectionistic tendencies often lead to self-criticism and feelings of inadequacy when they fail to meet their own high standards.\n\nSocial Support:\nEmilio's social support system is limited. They attend a veterans support group, which provides a sense of camaraderie and understanding. However, Emilio struggles to form deep connections within the group due to their difficulty opening up and fear of judgment.\n\nPersonal Strengths and Resilience Factors:\nDespite their struggles, Emilio possesses several strengths and resilience factors. Their ambitious nature and detail-oriented approach have helped them excel academically and develop a strong work ethic. Emilio's love for creative pursuits, such as cooking, singing, and writing, provides a potential avenue for self-expression and emotional release.\n\nPotential Challenges in Therapy:\nEmilio's perfectionism and self-reliance may pose challenges in therapy. They may have difficulty accepting help and may be resistant to challenging their negative self-beliefs. Emilio's reluctance to open up and trust others may also hinder the therapeutic process.\n\nTreatment Goals:\n1. Develop a more balanced and self-compassionate perspective towards themselves and their achievements.\n2. Explore and challenge negative thought patterns and perfectionistic tendencies.\n3. Increase engagement in enjoyable activities and hobbies to foster a sense of purpose and fulfillment.\n4. Improve sleep hygiene and establish a consistent daily routine to enhance overall well-being.\n5. Expand social support network and develop deeper connections with others.\n6. Explore career options and develop a plan for re-entering the workforce.\n7. Process and integrate Emilio's non-binary identity within the context of their religious and cultural background.\n\nCultural and Religious Considerations:\nEmilio's Hispanic heritage and conservative religious upbringing may influence their perception of mental health and help-seeking behaviors. They may feel conflicted between their traditional values and their personal identity and struggles. It is essential to approach Emilio's treatment with cultural sensitivity and explore how their background shapes their experience of depression and beliefs about therapy.",
  "characteristics": {
    "Age": "18-25",
    "Gender": "Non-binary",
    "Ethnicity": "Hispanic",
    "Education": "Master's Degree",
    "Occupation": "Unemployed",
    "Symptom_Severity": "Moderate",
    "Engagement_Level": "High",
    "Life_Events": [
      "Moving to a new city",
      "Workplace stress or burnout"
    ],
    "Family_Background": "Religious or conservative upbringing",
    "Hobbies_Interests": [
      "Cooking or baking",
      "Singing",
      "Writing",
      "Traveling",
      "Hiking or camping"
    ],
    "Social_Support": "Veterans support group",
    "Personality_Traits": [
      "Ambitious",
      "Detail-oriented"
    ],
    "Coping_Mechanisms": [
      "Exercise",
      "Perfectionism"
    ]
  }
}