{
  "profile": "Patient Profile: Dr. Arjun Patel\n\nBackstory:\nDr. Arjun Patel, a 52-year-old South Asian male, retired from his successful career as a research scientist two years ago. Born and raised in Mumbai, India, Arjun moved to the United States in his late twenties to pursue his doctoral degree in biochemistry. After completing his studies, he settled in a bustling city on the East Coast, where he built a life with his wife, Meera, and their two children.\n\nArjun's family background is a blended one; his parents divorced when he was young, and both remarried, creating a complex web of half-siblings and step-siblings. Despite the challenges of navigating these family dynamics, Arjun remained close with his immediate family members.\n\nThree years ago, Arjun and Meera decided to move to a quieter, suburban town to enjoy a slower pace of life as they approached retirement. However, shortly after the move, Meera was diagnosed with breast cancer. Arjun took early retirement to care for his wife, and though she is now in remission, the experience took a toll on both of them emotionally.\n\nCurrent Life Situation:\nSince retiring, Arjun has struggled to find a sense of purpose and meaning in his daily life. He misses the intellectual stimulation and social interaction that his career provided. While he enjoys spending time with his wife and adult children, who live nearby, he often feels disconnected from the world around him.\n\nArjun's hobbies include singing in a local community choir, playing board games with his family, and collecting vintage scientific instruments. However, he has found it difficult to engage in these activities with the same enthusiasm he once had.\n\nDepressive Symptoms and Impact:\nArjun's depression is characterized by persistent feelings of sadness, lack of energy, difficulty concentrating, and a loss of interest in previously enjoyed activities. He often feels irritable and on edge, which strains his relationships with his family members. Arjun's perfectionist tendencies have intensified, leading him to set unrealistically high standards for himself and feel discouraged when he cannot meet them.\n\nOnset and Progression:\nArjun's depressive symptoms first emerged during his wife's cancer treatment. The stress of caregiving, combined with the isolation he felt after retiring and moving to a new city, left him emotionally drained. As time passed and Meera's health improved, Arjun's symptoms did not subside. Instead, they gradually worsened, leading him to seek help.\n\nPrevious Treatment and Attitude Towards Therapy:\nArjun has never sought professional help for his depression before. He has always prided himself on his resilience and problem-solving abilities, believing that he should be able to overcome challenges on his own. However, at the encouragement of his wife and children, he has decided to give therapy a chance.\n\nCoping Mechanisms and Effectiveness:\nArjun's primary coping mechanisms include helping others, problem-solving, and, at times, anger or aggression. He finds solace in supporting his family members and engaging in intellectual pursuits, such as reading scientific journals. However, his perfectionism and tendency to suppress his emotions can lead to outbursts of anger when he feels overwhelmed.\n\nSocial Support System:\nArjun relies mainly on his family for support, particularly his wife, Meera. He is also close with his two adult children, who live nearby and visit often. While he has a few friends from his career and hobbies, he has struggled to maintain these relationships since retiring and moving to a new city.\n\nPersonal Strengths and Resilience Factors:\nDespite his depression, Arjun possesses several strengths and resilience factors. His extroverted nature allows him to connect with others easily, and his problem-solving skills have helped him navigate challenges throughout his life. He also finds a sense of purpose in helping others, which could be a valuable asset in therapy.\n\nPotential Challenges in Therapy:\nArjun's perfectionism and tendency to suppress his emotions may present challenges in therapy. He may struggle to open up about his feelings and set realistic goals for himself. Additionally, his strong sense of self-reliance may make it difficult for him to accept help from others, including his therapist.\n\nTreatment Goals:\n1. Develop healthier coping mechanisms for managing stress and difficult emotions.\n2. Reconnect with hobbies and interests that bring joy and fulfillment.\n3. Improve communication skills to strengthen relationships with family and friends.\n4. Explore new ways to find purpose and meaning in retirement.\n5. Learn to set realistic expectations for himself and practice self-compassion.\n\nCultural and Religious Beliefs:\nAs a Hindu, Arjun believes in the importance of family, duty, and finding balance in life. He may view his depression as a sign of personal weakness or a failure to fulfill his responsibilities. In therapy, it will be essential to address these beliefs and help Arjun develop a more compassionate understanding of his mental health.",
  "characteristics": {
    "Age": "46-55",
    "Gender": "Male",
    "Ethnicity": "South Asian",
    "Education": "Doctoral Degree",
    "Occupation": "Retired",
    "Symptom_Severity": "Moderate",
    "Engagement_Level": "High",
    "Life_Events": [
      "Moving to a new city"
    ],
    "Family_Background": "Blended family",
    "Hobbies_Interests": [
      "Singing",
      "Board games",
      "Collecting (specify)"
    ],
    "Social_Support": "Relies mainly on family for support",
    "Personality_Traits": [
      "Anxious",
      "Extroverted",
      "Resilient",
      "Perfectionist"
    ],
    "Coping_Mechanisms": [
      "Helping others",
      "Problem-solving",
      "Anger or aggression"
    ]
  }
}