{
  "profile": "Patient Profile: Robert Thompson\n\nBackstory:\nRobert Thompson, a 68-year-old Caucasian male, was born and raised in a small, close-knit town in the Midwest. He grew up in a supportive and loving family, with parents who instilled in him a strong work ethic and a passion for creativity. After graduating from high school, Robert joined the military, where he served for 10 years before being honorably discharged.\n\nDuring his time in the service, Robert experienced significant workplace stress and burnout, which led to his decision to leave the military. Upon returning to civilian life, he struggled to find stable employment and faced financial difficulties. Despite these challenges, Robert married his high school sweetheart, Sarah, and they had two children together.\n\nHowever, the strain of Robert's unemployment and financial stress took a toll on their marriage, ultimately leading to a divorce after 20 years together. The divorce was amicable, but it still left Robert feeling a sense of failure and loss.\n\nThree years ago, Robert experienced another devastating blow when his younger brother, Michael, passed away unexpectedly from a heart attack. Michael had been Robert's closest confidant and supporter, and his death left Robert feeling isolated and alone.\n\nCurrent Life Situation:\nRobert currently lives alone in a small apartment in his hometown. He has been unemployed for the past five years, struggling to find work due to his age and limited education. His children are grown and live in different states, and while they maintain contact, Robert often feels disconnected from them.\n\nRobert's daily life is marked by a sense of emptiness and lack of purpose. He spends much of his time engaged in DIY projects around his apartment, finding solace in the process of creating and repairing. He also enjoys writing and playing his guitar, activities that allow him to express his emotions and find temporary relief from his depressive symptoms.\n\nDepressive Symptoms and Impact:\nRobert's depressive symptoms have been present for the past seven years, with a moderate severity that has fluctuated over time. He experiences persistent feelings of sadness, hopelessness, and worthlessness, often questioning his value and purpose in life. Robert struggles with insomnia, finding it difficult to fall and stay asleep, which contributes to his fatigue and lack of energy during the day.\n\nRobert's depression has significantly impacted his motivation and ability to engage in activities he once enjoyed. He often feels disconnected from others and struggles to maintain relationships, leading to a sense of isolation and loneliness. His appetite has decreased, and he has experienced weight loss, which concerns his family and friends.\n\nOnset and Progression of Depression:\nRobert's depression first emerged during his time in the military, where he experienced significant stress and burnout. However, it was not until his divorce and subsequent unemployment that his symptoms intensified and became more persistent. The death of his brother three years ago further exacerbated his depression, leading to a period of severe symptoms that lasted for several months.\n\nPrevious Treatment History:\nRobert has never sought professional help for his depression, despite encouragement from his family and friends. He has a skeptical attitude towards therapy, believing that he should be able to overcome his struggles on his own. Robert's stoic and self-reliant nature has made it difficult for him to acknowledge his need for support and to reach out for help.\n\nCoping Mechanisms:\nRobert has developed several coping mechanisms to manage his depressive symptoms, some of which have been more adaptive than others. He often engages in DIY projects and creative pursuits, finding temporary relief in the process of creating and problem-solving. However, Robert also tends to overwork himself, spending excessive amounts of time on projects to avoid facing his emotional pain.\n\nIn moments of intense distress, Robert has engaged in self-harm, using physical pain as a means of coping with his emotional turmoil. He keeps these instances hidden from others, feeling ashamed and guilty about his behavior.\n\nSocial Support:\nDespite his reluctance to seek professional help, Robert has found some support through a local veterans support group. The group provides a sense of camaraderie and understanding, as many of its members have faced similar challenges in their transition to civilian life. Robert attends meetings sporadically but appreciates the opportunity to connect with others who share his experiences.\n\nPersonal Strengths and Resilience Factors:\nRobert possesses several personal strengths and resilience factors that have helped him cope with his depression. His detail-oriented and ambitious nature has enabled him to excel in his DIY projects and creative pursuits, providing a sense of accomplishment and purpose. Robert's close-knit family background has instilled in him a strong sense of loyalty and perseverance, even in the face of adversity.\n\nPotential Challenges in Therapy:\nRobert's skepticism towards therapy and his self-reliant nature may present challenges in engaging him in the therapeutic process. He may be resistant to exploring his emotions and may struggle to trust and open up to a therapist. Additionally, Robert's tendency to overwork himself and engage in self-harm may require targeted interventions to develop healthier coping strategies.\n\nTreatment Goals:\n1. Develop a therapeutic alliance and establish trust with Robert, acknowledging his strengths and validating his experiences.\n2. Explore and process Robert's feelings of loss, failure, and worthlessness related to his divorce, unemployment, and brother's death.\n3. Identify and challenge negative thought patterns and beliefs that contribute to Robert's depressive symptoms.\n4. Develop healthier coping strategies to replace self-harm and overworking, focusing on self-care and emotional regulation.\n5. Encourage Robert to engage more consistently with his veterans support group and explore additional sources of social support.\n6. Collaborate with Robert to identify meaningful goals and activities that align with his values and provide a sense of purpose.\n7. Address Robert's sleep difficulties and appetite changes, developing strategies to improve his overall physical health and well-being.\n\nCultural and Personal Beliefs:\nRobert's Midwestern upbringing has instilled in him a strong sense of self-reliance and stoicism, which may influence his attitude towards therapy and his willingness to express emotions. His military background may also contribute to a belief in the importance of mental toughness and resilience, making it challenging for him to acknowledge and address his emotional needs. It will be essential to approach Robert with cultural sensitivity and to work within his belief system to develop a therapeutic approach that resonates with his values and experiences.",
  "characteristics": {
    "Age": "66+",
    "Gender": "Male",
    "Ethnicity": "Caucasian",
    "Education": "High School",
    "Occupation": "Unemployed",
    "Symptom_Severity": "Moderate",
    "Engagement_Level": "High",
    "Life_Events": [
      "Workplace stress or burnout",
      "Divorce or relationship breakup",
      "Death of a loved one"
    ],
    "Family_Background": "Supportive and close-knit",
    "Hobbies_Interests": [
      "DIY projects",
      "Writing",
      "Playing musical instruments"
    ],
    "Social_Support": "Veterans support group",
    "Personality_Traits": [
      "Detail-oriented",
      "Ambitious"
    ],
    "Coping_Mechanisms": [
      "Self-harm",
      "Overworking",
      "Problem-solving"
    ]
  }
}