{
  "profile": "Patient Profile: Mei Xiang\n\nBackstory:\nMei Xiang, a 68-year-old transgender woman of East Asian descent, was born and raised in a small, conservative town in China. As the only child of her parents, Mei faced immense pressure to conform to societal norms and carry on the family name. However, from a young age, Mei knew that her true identity did not align with the gender she was assigned at birth.\n\nAfter completing her Bachelor's degree in Engineering, Mei moved to a larger city, seeking a more accepting environment. There, she found a community of like-minded individuals and began her transition journey. During this time, Mei also became a parent through adoption, fulfilling her lifelong dream of having a family.\n\nCurrent Life Situation:\nMei is currently unemployed, having retired from her successful career as an engineer several years ago. She lives alone in a small apartment, with her adult child living nearby. Mei's limited social connections consist mainly of a few close friends from her transgender support group and a neighbor with whom she occasionally shares meals.\n\nMei spends her days working on various DIY projects, such as woodworking and crafting, which bring her a sense of purpose and accomplishment. She also enjoys collecting vintage postcards, a hobby that allows her to indulge her love of travel and adventure from the comfort of her home.\n\nDepressive Symptoms and Impact:\nMei's depressive symptoms are relatively mild but have been persistent for the past two years. She often experiences feelings of loneliness, worthlessness, and a lack of motivation. These symptoms have made it difficult for Mei to engage in her usual hobbies and maintain her social connections.\n\nOnset and Progression of Depression:\nMei's depression first emerged after her retirement, when she found herself struggling to adapt to a life without the structure and sense of purpose that her career provided. The loss of her professional identity, combined with the increasing physical limitations that come with age, left Mei feeling adrift and disconnected from her sense of self.\n\nPrevious Treatment History:\nMei has never sought professional help for her depression, as she believes that her symptoms are a natural consequence of aging and that she should be able to manage them on her own. However, her growing awareness of the impact of her depression on her quality of life has led her to consider therapy.\n\nCoping Mechanisms and Effectiveness:\nMei's primary coping mechanisms include perfectionism, humor, journaling, and seeking social support. Her perfectionism, while driving her to excel in her DIY projects, often leads to self-criticism and feelings of inadequacy. Mei's sense of humor and ability to find joy in small moments help to alleviate her depressive symptoms, but only temporarily. Journaling has become a valuable outlet for Mei to express her thoughts and emotions, providing her with a sense of clarity and self-understanding. However, her limited social connections make it difficult for Mei to consistently access the social support she craves.\n\nSocial Support System:\nMei's social support system is limited but deeply valued. Her transgender support group provides a safe space for her to share her experiences and receive validation and encouragement. Mei's neighbor, a widow who shares her love of travel, has become a cherished friend and confidant.\n\nPersonal Strengths and Resilience Factors:\nMei's adventurous spirit and easy-going nature have allowed her to adapt to various challenges throughout her life, from her gender transition to her retirement. Her sensitivity and empathy have enabled her to form deep, meaningful connections with others, even in the face of societal stigma and rejection.\n\nPotential Challenges in Therapy:\nMei's perfectionism and self-critical nature may hinder her ability to fully engage in therapy and accept support from her therapist. Additionally, her cultural background and generational beliefs about mental health may make it difficult for her to openly discuss her emotions and experiences.\n\nTreatment Goals:\n1. Develop healthy coping strategies to manage depressive symptoms and improve overall well-being.\n2. Cultivate a stronger sense of self-worth and purpose outside of her professional identity.\n3. Expand her social support network and engage in meaningful activities that align with her values and interests.\n4. Address and challenge internalized stigma and negative beliefs related to her gender identity and mental health.\n5. Improve communication skills and emotional vulnerability to deepen connections with loved ones and her therapist.\n\nCultural and Personal Beliefs:\nMei's East Asian cultural background emphasizes the importance of family, filial piety, and stoicism in the face of adversity. These values have shaped her belief that she should be able to manage her depression independently and that seeking help is a sign of weakness. Additionally, her experiences of stigma and rejection related to her gender identity have led her to be cautious about disclosing her full self to others, including mental health professionals.",
  "characteristics": {
    "Age": "66+",
    "Gender": "Transgender",
    "Ethnicity": "East Asian",
    "Education": "Bachelor's Degree",
    "Occupation": "Unemployed",
    "Symptom_Severity": "Mild",
    "Engagement_Level": "High",
    "Life_Events": [
      "Becoming a parent"
    ],
    "Family_Background": "Only child",
    "Hobbies_Interests": [
      "DIY projects",
      "Collecting (specify)",
      "Traveling"
    ],
    "Social_Support": "Limited social connections",
    "Personality_Traits": [
      "Easy-going",
      "Sensitive",
      "Adventurous"
    ],
    "Coping_Mechanisms": [
      "Perfectionism",
      "Humor or laughter",
      "Journaling",
      "Seeking social support"
    ]
  }
}